fake_gen/__init__.py
fake_gen/base.py
fake_gen/childrentree.py
fake_gen/compat.py
fake_gen/dictionary.py
fake_gen/errors.py
fake_gen/metaclasses.py
fake_gen/extra/__init__.py
fake_gen/extra/mongodb.py
fake_gen/factories/__init__.py
fake_gen/factories/datetimes.py
fake_gen/factories/fake.py
fake_gen/factories/generic.py
fake_gen/factories/numeric.py
fake_gen/factories/sequences.py
fake_gen/factories/statistical.py
fake_gen/factories/strings.py
fake_gen-1.0.0b2.dist-info/LICENSE
fake_gen-1.0.0b2.dist-info/METADATA
fake_gen-1.0.0b2.dist-info/WHEEL
fake_gen-1.0.0b2.dist-info/top_level.txt
fake_gen-1.0.0b2.dist-info/RECORD
