Metadata-Version: 2.1
Name: fake-gen
Version: 1.0.0b2
Summary: A small package that helps generate content to fill databases for tests
Home-page: http://github.com/psafont/fake-gen
Author: Arie Bro
Author-email: ariebro@gmail.com
Maintainer: Pau Ruiz Safont
Maintainer-email: psafont@ebi.ac.uk
License: MIT
Keywords: factory testing test unittest mongo data generator database json elasticsearch
Platform: UNKNOWN
Classifier: Development Status :: 3 - Alpha
Classifier: Intended Audience :: Developers
Classifier: Topic :: Software Development :: Testing
Classifier: License :: OSI Approved :: MIT License
Classifier: Programming Language :: Python :: 2
Classifier: Programming Language :: Python :: 2.7
Classifier: Programming Language :: Python :: 3
Classifier: Programming Language :: Python :: 3.4
Classifier: Programming Language :: Python :: 3.5
Classifier: Programming Language :: Python :: 3.6
Classifier: Programming Language :: Python :: 3.7
Requires-Dist: faker (>0.8.0)
Provides-Extra: dev
Requires-Dist: pymongo ; extra == 'dev'
Provides-Extra: mongo
Requires-Dist: pymongo ; extra == 'mongo'
Provides-Extra: test
Requires-Dist: pytest ; extra == 'test'
Requires-Dist: pymongo ; extra == 'test'
